amtFMC5030/FMC_funct.py
amtFMC5030/__init__.py
amtFMC5030/debug_funct.py
amtFMC5030/examples/labview_examples/firmware_version.vi
amtFMC5030/examples/labview_examples/initialize.vi
amtFMC5030/examples/labview_examples/receive.vi
amtFMC5030/examples/labview_examples/transceive.vi
amtFMC5030/examples/labview_examples/transmit.vi
amtFMC5030/examples/python_examples/change_ref_clk.py
amtFMC5030/examples/python_examples/firmware.py
amtFMC5030/examples/python_examples/initialize.py
amtFMC5030/examples/python_examples/receive.py
amtFMC5030/examples/python_examples/transceive.py
amtFMC5030/examples/python_examples/transmit.py
amtFMC5030-1.0.0.dist-info/LICENSE.txt
amtFMC5030-1.0.0.dist-info/METADATA
amtFMC5030-1.0.0.dist-info/WHEEL
amtFMC5030-1.0.0.dist-info/entry_points.txt
amtFMC5030-1.0.0.dist-info/top_level.txt
amtFMC5030-1.0.0.dist-info/RECORD
