Metadata-Version: 2.1
Name: amtFMC5030
Version: 1.0.0
Summary: Amtery Python library for FMC5030.
Author-email: yingju <yingju.chen@hxltd.com>
Maintainer: Amtery
Maintainer-email: yingju <yingju.chen@hxltd.com>
License: MIT License
Project-URL: Homepage, https://www.amtery.com/en
Project-URL: Documentation, https://github.com/yjchenhx/amtFMC_examples
Classifier: Programming Language :: Python :: 3
Classifier: License :: OSI Approved :: MIT License
Requires-Python: >=3.6
License-File: LICENSE.txt
Requires-Dist: paramiko
Requires-Dist: pyadi-iio <=0.0.16
Requires-Dist: pylibiio <=0.25
Requires-Dist: numpy
Provides-Extra: examples
Requires-Dist: thread6 ; extra == 'examples'
Requires-Dist: matplotlib ; extra == 'examples'
Requires-Dist: scipy ; extra == 'examples'
